bowerbirds/__init__.py
bowerbirds/cli.py
bowerbirds/config.py
bowerbirds/core.py
bowerbirds/create_dir.py
bowerbirds/full_meta.py
bowerbirds/lite_llm.py
bowerbirds/pipeline.py
bowerbirds/summary.py
bowerbirds-0.1.1.dist-info/licenses/LICENSE
bowerbirds-0.1.1.dist-info/METADATA
bowerbirds-0.1.1.dist-info/WHEEL
bowerbirds-0.1.1.dist-info/entry_points.txt
bowerbirds-0.1.1.dist-info/top_level.txt
bowerbirds-0.1.1.dist-info/RECORD
