Metadata-Version: 2.4
Name: bowerbirds
Version: 0.1.1
Summary: Convert unstructured AI project directories into structured, professional-ready directories.
Author-email: Shubham Aggarwal <shubham_agg@alumni.iitm.ac.in>
License: MIT
Requires-Python: >=3.9
License-File: LICENSE
Requires-Dist: transformers>=4.30.0
Requires-Dist: torch>=1.13.0
Requires-Dist: litellm
Dynamic: license-file
